{
  "fields": {
    "area": "78889222-8f08-40b6-92b1-73f4a98fc533",
    "created_in_mneia": "2025-02-12 08:46:04.348630+00:00",
    "edition": "1η έκδοση",
    "format": "78a2d4eb-0794-48bd-ad88-735413aa5395",
    "isbn": "9789606882746",
    "name": "Οι βερβελίδες της Αμάλθειας, αναφορά στο Χόμο Σάπιενς: αυτοβιογραφία",
    "pages_number": 332,
    "publication_date_day": null,
    "publication_date_month": 12,
    "publication_date_year": 2012,
    "updated_in_mneia": "2025-02-12 08:46:04.348655+00:00"
  },
  "model": "mneia_backend.book",
  "pk": "d0af1eeb-92e6-47f6-a440-bf8f4c7d175b"
}